TFOD_Automatic/__init__.py
TFOD_Automatic/install/__init__.py
TFOD_Automatic/install/check_installed_package.py
TFOD_Automatic/model/__init__.py
TFOD_Automatic/model/_buildmodel.py
TFOD_Automatic/model/_createmodel.py
TFOD_Automatic/setup/__init__.py
TFOD_Automatic/setup/_cloneModel.py
TFOD_Automatic/setup/_protosetup.py
TFOD_Automatic-1.4.dist-info/METADATA
TFOD_Automatic-1.4.dist-info/WHEEL
TFOD_Automatic-1.4.dist-info/top_level.txt
TFOD_Automatic-1.4.dist-info/RECORD
